{"description":"Geospatial data about Nenmeni Grama Panchayat (Wayanad district)","districtlabel":"Wayanad district","draft":false,"enarticle":"","images":["/img/Q13112975.png"],"iscjklanguage":false,"len":"Nenmeni Grama Panchayat","lgdcode":"221932","lml":"നെന്മേനി ഗ്രാമ പഞ്ചായത്ത്","lsgcode":"G120302","mlarticle":"https://ml.wikipedia.org/wiki/%E0%B4%A8%E0%B5%86%E0%B4%A8%E0%B5%8D%E0%B4%AE%E0%B5%87%E0%B4%A8%E0%B4%BF_%E0%B4%97%E0%B5%8D%E0%B4%B0%E0%B4%BE%E0%B4%AE%E0%B4%AA%E0%B4%9E%E0%B5%8D%E0%B4%9A%E0%B4%BE%E0%B4%AF%E0%B4%A4%E0%B5%8D%E0%B4%A4%E0%B5%8D","mldistrictlabel":"വയനാട് ജില്ല","qid":"Q13112975","title":"Nenmeni Grama Panchayat | നെന്മേനി ഗ്രാമ പഞ്ചായത്ത് | വയനാട് ജില്ല | Wayanad district","wards":"23"}